card_data_parsers/__init__.py
card_data_parsers/log.py
card_data_parsers/utils.py
card_data_parsers/models/__init__.py
card_data_parsers/models/amex_transaction.py
card_data_parsers/models/cdf_transaction.py
card_data_parsers/models/happay_transaction.py
card_data_parsers/models/s3df_transaction.py
card_data_parsers/models/transaction.py
card_data_parsers/models/vcf_transaction.py
card_data_parsers/parsers/__init__.py
card_data_parsers/parsers/amex_parser.py
card_data_parsers/parsers/cdf_parser.py
card_data_parsers/parsers/happay_parser.py
card_data_parsers/parsers/parser.py
card_data_parsers/parsers/s3df_parser.py
card_data_parsers/parsers/vcf_parser.py
card_data_parsers-0.17.0.dist-info/LICENSE
card_data_parsers-0.17.0.dist-info/METADATA
card_data_parsers-0.17.0.dist-info/WHEEL
card_data_parsers-0.17.0.dist-info/top_level.txt
card_data_parsers-0.17.0.dist-info/RECORD
