Metadata-Version: 2.1
Name: card_data_parsers
Version: 0.17.0
Summary: Parsing bank feed data files
Home-page: https://www.fylehq.com
Author: Siva Narayanan
Author-email: siva@fyle.in
License: MIT
Keywords: fyle,api,python,sdk,cards,parsers,amex,visa,cdf,vcf,s3df,happay,mastercard,diners club
Classifier: Intended Audience :: Developers
Classifier: Programming Language :: Python :: 3
Classifier: License :: OSI Approved :: MIT License
Classifier: Operating System :: OS Independent
License-File: LICENSE
Requires-Dist: pycountry>=18.5.26
Requires-Dist: typing-extensions>=3.10.0.0
Requires-Dist: jsondiff>=1.2.0
Requires-Dist: dataclasses>=0.6
